mcp_vcd/__init__.py
mcp_vcd/server.py
mcp_vcd-0.1.1.dist-info/METADATA
mcp_vcd-0.1.1.dist-info/WHEEL
mcp_vcd-0.1.1.dist-info/entry_points.txt
mcp_vcd-0.1.1.dist-info/licenses/LICENSE
mcp_vcd-0.1.1.dist-info/RECORD
