Metadata-Version: 2.4
Name: mcp-vcd
Version: 0.1.1
Summary: A model context protocol (MCP) server for value change dump (VCD) waveforms.
License-File: LICENSE
Requires-Python: >=3.13
Requires-Dist: httpx>=0.28.1
Requires-Dist: ipykernel>=6.29.5
Requires-Dist: mcp>=1.1.2
